openterrace/__init__.py
openterrace/analytical_functions.py
openterrace/bed_substances/ATS50.py
openterrace/bed_substances/ATS58.py
openterrace/bed_substances/__init__.py
openterrace/bed_substances/magnetite.py
openterrace/bed_substances/swedish_diabase.py
openterrace/convection_schemes/__init__.py
openterrace/convection_schemes/upwind_1d.py
openterrace/diffusion_schemes/__init__.py
openterrace/diffusion_schemes/central_difference_1d.py
openterrace/domains/__init__.py
openterrace/domains/block_1d.py
openterrace/domains/cylinder_1d.py
openterrace/domains/hollow_sphere_1d.py
openterrace/domains/lumped.py
openterrace/domains/sphere_1d.py
openterrace/fluid_substances/__init__.py
openterrace/fluid_substances/air.py
openterrace/fluid_substances/water.py
openterrace/openterrace.py
openterrace/postprocessing/__init__.py
openterrace/postprocessing/animation.py
openterrace/postprocessing/panda_dataframe.py
openterrace/tests/test_advection_step_function.py
openterrace/tests/test_energy_conservation.py
openterrace/tests/test_heat_diffusion_sphere.py
openterrace/tests/test_heat_diffusion_wall.py
openterrace-0.1.4.dist-info/LICENSE.txt
openterrace-0.1.4.dist-info/METADATA
openterrace-0.1.4.dist-info/WHEEL
openterrace-0.1.4.dist-info/RECORD
