Metadata-Version: 2.1
Name: openterrace
Version: 0.1.4
Summary: OpenTerrace: A fast, flexible and extendable Python framework for packed bed thermal energy storage simulations
Home-page: https://github.com/OpenTerrace/openterrace-python
License: MIT
Keywords: Thermal energy storage,Packed bed,Simulation,Heat transfer,Phase change material,PCM,Python
Author: Jakob Hærvig
Maintainer: Jakob Hærvig
Maintainer-email: jakob.haervig@gmail.com
Requires-Python: >=3.11.8,<4.0.0
Classifier: License :: OSI Approved :: MIT License
Classifier: Programming Language :: Python :: 3
Classifier: Programming Language :: Python :: 3.12
Requires-Dist: matplotlib (>=3.8.3,<4.0.0)
Requires-Dist: numba (>=0.59.0,<0.60.0)
Requires-Dist: numpy (>=1.26.4,<2.0.0)
Requires-Dist: pytest-xdist (>=3.5.0,<4.0.0)
Requires-Dist: scipy (>=1.12.0,<2.0.0)
Requires-Dist: tqdm (>=4.66.2,<5.0.0)
Project-URL: Bug Tracker, https://github.com/OpenTerrace/openterrace-python/issues
Project-URL: Documentation, https://openterrace.github.io/openterrace-python/
Project-URL: Repository, https://github.com/OpenTerrace/openterrace-python
